{
  "bug_id": "1793423",
  "summary": "Crash in [@ PLDHashTable::EntryStore::IsAllocated | PLDHashTable::Search | nsTHashtable<T>::GetEntry | nsBaseHashtable<T>::Lookup | mozilla::a11y::AccAttributes::GetAttribute]",
  "product": "Core",
  "component": "Disability Access APIs",
  "crash_signature": "[@ PLDHashTable::EntryStore::IsAllocated | PLDHashTable::Search | nsTHashtable<T>::GetEntry | nsBaseHashtable<T>::Lookup | mozilla::a11y::AccAttributes::GetAttribute]",
  "extraction_timestamp": "2025-12-08T21:52:06.650782",
  "fixing_commits_count": 1,
  "fixing_files_count": 1,
  "regressor_commits_count": 2,
  "regressor_files_count": 26,
  "has_regression": true
}