{
  "bug_id": "1996880",
  "summary": "Crash in [@ mozilla::gfx::GPUProcessManager::EnsureGPUReady]",
  "product": "Core",
  "component": "Graphics",
  "creation_time": "2025-10-28T16:44:35Z",
  "crash_signatures": [
    "mozilla::gfx::GPUProcessManager::EnsureGPUReady"
  ],
  "bugzilla_url": "https://bugzilla.mozilla.org/show_bug.cgi?id=1996880",
  "socorro_crash_ids": [
    "b394f4b0-dd09-47e8-b988-c355f0251022"
  ],
  "stack_source": "socorro",
  "crash_id": "b394f4b0-dd09-47e8-b988-c355f0251022",
  "socorro_metadata": {
    "signature": "",
    "crash_reason": "",
    "moz_crash_reason": "",
    "crashing_thread": {
      "index": 0,
      "name": "MainThread"
    }
  },
  "stack_trace": {
    "source": "socorro",
    "crash_id": "b394f4b0-dd09-47e8-b988-c355f0251022",
    "frames": [
      {
        "frame_index": 0,
        "module": "xul.dll",
        "function": "mozilla::gfx::GPUProcessManager::EnsureGPUReady()",
        "source": "gfx/ipc/GPUProcessManager.cpp:464",
        "file": "gfx/ipc/GPUProcessManager.cpp",
        "line": 464,
        "trust": "context"
      },
      {
        "frame_index": 1,
        "module": "xul.dll",
        "function": "nsIWidget::CreateCompositorSession(int, int, mozilla::layers::CompositorOptions*)",
        "source": "widget/nsIWidget.cpp:1488",
        "file": "widget/nsIWidget.cpp",
        "line": 1488,
        "trust": "cfi"
      },
      {
        "frame_index": 2,
        "module": "xul.dll",
        "function": "nsIWidget::CreateCompositor(int, int)",
        "source": "widget/nsIWidget.cpp:1598",
        "file": "widget/nsIWidget.cpp",
        "line": 1598,
        "trust": "cfi"
      },
      {
        "frame_index": 3,
        "module": "xul.dll",
        "function": "nsIWidget::CreateCompositor()",
        "source": "widget/nsIWidget.cpp:1048",
        "file": "widget/nsIWidget.cpp",
        "line": 1048,
        "trust": "cfi"
      },
      {
        "frame_index": 4,
        "module": "xul.dll",
        "function": "nsWindow::CreateCompositor()",
        "source": "widget/windows/nsWindowGfx.cpp:398",
        "file": "widget/windows/nsWindowGfx.cpp",
        "line": 398,
        "trust": "cfi"
      },
      {
        "frame_index": 5,
        "module": "xul.dll",
        "function": "nsWindow::GetWindowRenderer()",
        "source": "widget/windows/nsWindow.cpp:3821",
        "file": "widget/windows/nsWindow.cpp",
        "line": 3821,
        "trust": "cfi"
      },
      {
        "frame_index": 6,
        "module": "xul.dll",
        "function": "nsWindow::OnPaint()",
        "source": "widget/windows/nsWindowGfx.cpp:170",
        "file": "widget/windows/nsWindowGfx.cpp",
        "line": 170,
        "trust": "cfi"
      },
      {
        "frame_index": 7,
        "module": "xul.dll",
        "function": "nsWindow::ProcessMessageInternal(unsigned int, unsigned int&, long&, long*)",
        "source": "widget/windows/nsWindow.cpp:5106",
        "file": "widget/windows/nsWindow.cpp",
        "line": 5106,
        "trust": "cfi"
      },
      {
        "frame_index": 8,
        "module": "xul.dll",
        "function": "nsWindow::ProcessMessage(unsigned int, unsigned int&, long&, long*)",
        "source": "widget/windows/nsWindow.cpp:4748",
        "file": "widget/windows/nsWindow.cpp",
        "line": 4748,
        "trust": "inlined"
      },
      {
        "frame_index": 8,
        "module": "xul.dll",
        "function": "nsWindow::WindowProcInternal(HWND__*, unsigned int, unsigned int, long)",
        "source": "widget/windows/nsWindow.cpp:4700",
        "file": "widget/windows/nsWindow.cpp",
        "line": 4700,
        "trust": "cfi"
      },
      {
        "frame_index": 9,
        "module": "xul.dll",
        "function": "CallWindowProcCrashProtected(long (*)(HWND__*, unsigned int, unsigned int, long), HWND__*, unsigned int, unsigned int, long)",
        "source": "xpcom/base/nsCrashOnException.cpp:27",
        "file": "xpcom/base/nsCrashOnException.cpp",
        "line": 27,
        "trust": "cfi"
      },
      {
        "frame_index": 10,
        "module": "xul.dll",
        "function": "nsWindow::WindowProc(HWND__*, unsigned int, unsigned int, long)",
        "source": "widget/windows/nsWindow.cpp:4659",
        "file": "widget/windows/nsWindow.cpp",
        "line": 4659,
        "trust": "cfi"
      },
      {
        "frame_index": 11,
        "module": "user32.dll",
        "function": "_InternalCallWinProc",
        "source": "",
        "file": "",
        "line": null,
        "trust": "cfi"
      },
      {
        "frame_index": 12,
        "module": "user32.dll",
        "function": "UserCallWinProcCheckWow(_ACTIVATION_CONTEXT*, long (*)(tagWND*, unsigned int, unsigned int, long), HWND__*, _WM_VALUE, unsigned int, long, void*, int)",
        "source": "",
        "file": "",
        "line": null,
        "trust": "frame_pointer"
      },
      {
        "frame_index": 13,
        "module": "user32.dll",
        "function": "DispatchClientMessage",
        "source": "",
        "file": "",
        "line": null,
        "trust": "cfi"
      },
      {
        "frame_index": 14,
        "module": "user32.dll",
        "function": "__fnDWORD",
        "source": "",
        "file": "",
        "line": null,
        "trust": "cfi"
      },
      {
        "frame_index": 15,
        "module": "ntdll.dll",
        "function": "KiUserCallbackDispatcher",
        "source": "",
        "file": "",
        "line": null,
        "trust": "cfi"
      }
    ],
    "frame_count": 17
  }
}