{
  "bug_id": "1565501",
  "summary": "Crash in [@ OOM | large | NS_ABORT_OOM | nsTArray_base<T>::EnsureCapacity<T> | nsTArray_Impl<T>::AppendElements<T> | mozilla::MediaSpan::Append]",
  "product": "Core",
  "component": "Audio/Video: Playback",
  "crash_signature": "[@ OOM | large | NS_ABORT_OOM | nsTArray_base<T>::EnsureCapacity<T> | nsTArray_Impl<T>::AppendElements<T> | mozilla::MediaSpan::Append]\r\n[@ OOM | large | mozalloc_abort | mozalloc_handle_oom | moz_xrealloc | nsTArray_base<T>::EnsureCapacity<T> | nsTArray_Impl<T>::AppendElements<T> | mozilla::MediaSpan::Append]\r\n[@ OOM | large | NS_ABORT_OOM | nsTArray_base<T>::EnsureCapacity<T> | mozilla::MediaSpan::Append]",
  "extraction_timestamp": "2025-12-08T21:53:53.077578",
  "fixing_commits_count": 1,
  "fixing_files_count": 1,
  "regressor_commits_count": 4,
  "regressor_files_count": 34,
  "has_regression": true
}