{
  "bug_id": "1905002",
  "summary": "Intermittent application crashed [@ mozilla::dom::XMLHttpRequestWorker::SetResponseToNetworkError] | single tracking bug",
  "product": "Core",
  "component": "DOM: Networking",
  "crash_signature": "[@ mozilla::dom::XMLHttpRequestWorker::SetResponseToNetworkError]",
  "extraction_timestamp": "2025-12-08T21:51:26.125345",
  "fixing_commits_count": 1,
  "fixing_files_count": 1,
  "regressor_commits_count": 1,
  "regressor_files_count": 8,
  "has_regression": true
}